setup.py
pyetl_framework/__init__.py
pyetl_framework/app.py
pyetl_framework/config.py
pyetl_framework/worker.py
pyetl_framework.egg-info/PKG-INFO
pyetl_framework.egg-info/SOURCES.txt
pyetl_framework.egg-info/dependency_links.txt
pyetl_framework.egg-info/entry_points.txt
pyetl_framework.egg-info/requires.txt
pyetl_framework.egg-info/top_level.txt
pyetl_framework/../README.md
pyetl_framework/../VERSION
pyetl_framework/../requirements.txt
pyetl_framework/lib/__init__.py
pyetl_framework/lib/etl_job.py
pyetl_framework/lib/extractor.py
pyetl_framework/lib/loader.py
pyetl_framework/lib/pipeline.py
pyetl_framework/lib/pipeline_manager.py
pyetl_framework/lib/transformer.py
pyetl_framework/templates/layout.jade
pyetl_framework/templates/pipeline.jade
pyetl_framework/templates/pipeline_start.jade
pyetl_framework/templates/pipelines.jade