Metadata-Version: 1.1
Name: pyetl-framework
Version: 0.0.49
Summary: A python based scraper for any data source.
Home-page: https://github.com/jonathanporta/pyetl_framework
Author: Jonathan Porta
Author-email: jonathan@jonathanPorta.com
License: MIT
Keywords: etl scraping
Platform: UNKNOWN
Classifier: Development Status :: 3 - Alpha
Classifier: Intended Audience :: Developers
Classifier: Topic :: Software Development :: Build Tools
Classifier: License :: OSI Approved :: MIT License
Classifier: Programming Language :: Python :: 3.4
Classifier: Programming Language :: Python :: 3.5
